jitter/JITTER_DESIGN_AND_USAGE.md
jitter/__init__.py
jitter/scaffold.py
jitter/core/__init__.py
jitter/core/handler.py
jitter/generation/__init__.py
jitter/generation/generator.py
jitter/generation/llm.py
jitter/generation/types.py
jitter/generation/ui.py
jitter/generation/vs_code_diff.py
jitter/generation/vscode_function_diff.py
jitter/source_manipulation/__init__.py
jitter/source_manipulation/hot_reload.py
jitter/source_manipulation/inspection.py
jitter/source_manipulation/replacement.py
jitter_llm-0.3.2.dist-info/METADATA
jitter_llm-0.3.2.dist-info/WHEEL
jitter_llm-0.3.2.dist-info/entry_points.txt
jitter_llm-0.3.2.dist-info/licenses/LICENSE
jitter_llm-0.3.2.dist-info/RECORD
