Metadata-Version: 2.4
Name: jitter-llm
Version: 0.3.2
Summary: Build your program Just-in-Time with LLM Assistance
Project-URL: Homepage, https://github.com/JasonSteving99/Jitter
Author-email: Jason Steving <jasonmail99@gmail.com>
License:                                  Apache License
License-File: LICENSE
Classifier: Development Status :: 3 - Alpha
Classifier: Intended Audience :: Developers
Classifier: License :: OSI Approved :: Apache Software License
Classifier: Programming Language :: Python :: 3 :: Only
Classifier: Programming Language :: Python :: 3.10
Classifier: Programming Language :: Python :: 3.11
Classifier: Programming Language :: Python :: 3.12
Classifier: Topic :: Software Development :: User Interfaces
Requires-Python: >=3.10
Requires-Dist: google-genai>=1.19.0
Requires-Dist: pydantic>=2.11.5
Provides-Extra: cli
Requires-Dist: asyncclick>=8.1.8; extra == 'cli'
Requires-Dist: claude-code-sdk>=0.0.10; extra == 'cli'
